{
  "schemaId": "agent.semantic-protocols.provider-workspace-install",
  "schemaVersion": "1",
  "schemaAuthority": "https://tao3k.github.io/agent-semantic-protocols/schemas/",
  "providerId": "rs-harness",
  "binary": "rs-harness",
  "workspaceArtifact": {
    "root": "languages/rust-lang-project-harness/target/release/rs-harness",
    "entrypoint": "."
  },
  "workspaceBuild": {
    "program": "cargo",
    "args": [
      "build",
      "--locked",
      "--release",
      "--manifest-path",
      "Cargo.toml",
      "--features",
      "cli",
      "--bin",
      "rs-harness"
    ],
    "workingDirectory": "languages/rust-lang-project-harness",
    "sourceSnapshotAnchors": [
      "languages/rust-lang-project-harness/Cargo.toml",
      "languages/rust-lang-project-harness/Cargo.lock"
    ],
    "derivedPaths": [
      "languages/rust-lang-project-harness/target"
    ],
    "env": {}
  }
}
